LICENSE
MANIFEST.in
README.md
setup.cfg
setup.py
bin/surf.py
pitted/__init__.py
pitted.egg-info/PKG-INFO
pitted.egg-info/SOURCES.txt
pitted.egg-info/dependency_links.txt
pitted.egg-info/not-zip-safe
pitted.egg-info/top_level.txt
pitted/gnar/wickedbits