Metadata-Version: 1.0
Name: pitted
Version: 0.3.4
Summary: Get pitted, so pitted.
Home-page: https://github.com/kortox/pitted
Author: kortox
Author-email: kortox@gmail.com
License: MIT
Keywords: pitted drop in get so
Platform: UNKNOWN
